LICENSE
naskpy/__init__.py
naskpy/image_processing.py
naskpy/io.py
naskpy/main.py
naskpy/strings.py
naskpy-0.1.1.dist-info/LICENSE
naskpy-0.1.1.dist-info/WHEEL
naskpy-0.1.1.dist-info/METADATA
naskpy-0.1.1.dist-info/RECORD
