Metadata-Version: 2.1
Name: naskpy
Version: 0.1.1
Summary: Tools, modules and functions that I use regularly while coding in Python
Home-page: https://github.com/naskio/naskpy
License: MIT
Keywords: Python,Python3,library,utilities
Author: Mehdi Nassim KHODJA
Author-email: khodjamehdinassim@gmail.com
Maintainer: Mehdi Nassim KHODJA
Maintainer-email: khodjamehdinassim@gmail.com
Requires-Python: >=3.7,<3.10
Classifier: Environment :: Console
Classifier: License :: OSI Approved :: MIT License
Classifier: Operating System :: OS Independent
Classifier: Programming Language :: Python :: 3
Classifier: Programming Language :: Python :: 3.7
Classifier: Programming Language :: Python :: 3.8
Classifier: Programming Language :: Python :: 3.9
Classifier: Topic :: Software Development :: Libraries :: Python Modules
Requires-Dist: Pillow (==8.4)
Requires-Dist: pendulum (>=2.1.2,<3.0.0)
Requires-Dist: requests (>=2.26.0,<3.0.0)
Project-URL: Documentation, https://py.nask.io/
Project-URL: Repository, https://github.com/naskio/naskpy
Project-URL: issues, https://github.com/naskio/naskpy/issues
